sphinxcontrib_requirements-0.3.dev20201103-py3.8-nspkg.pth
sphinxcontrib/requirements.css
sphinxcontrib/requirements.py
sphinxcontrib_requirements-0.3.dev20201103.dist-info/AUTHORS
sphinxcontrib_requirements-0.3.dev20201103.dist-info/METADATA
sphinxcontrib_requirements-0.3.dev20201103.dist-info/WHEEL
sphinxcontrib_requirements-0.3.dev20201103.dist-info/namespace_packages.txt
sphinxcontrib_requirements-0.3.dev20201103.dist-info/top_level.txt
sphinxcontrib_requirements-0.3.dev20201103.dist-info/RECORD
